xlsx2pandas/__init__.py
xlsx2pandas/cli.py
xlsx2pandas/extractor.py
xlsx2pandas/openpyxl_utils.py
xlsx2pandas/utils.py
xlsx2pandas/dataframe_construction/__init__.py
xlsx2pandas/dataframe_construction/general_constructor.py
xlsx2pandas/dataframe_construction/utils.py
xlsx2pandas/header_separation/__init__.py
xlsx2pandas/header_separation/general_separator.py
xlsx2pandas/header_separation/utils.py
xlsx2pandas/table_detection/__init__.py
xlsx2pandas/table_detection/general_detector.py
xlsx2pandas/table_detection/utils.py
xlsx2pandas-0.1.0.data/scripts/xlsx2pandas
xlsx2pandas-0.1.0.dist-info/LICENSE
xlsx2pandas-0.1.0.dist-info/METADATA
xlsx2pandas-0.1.0.dist-info/WHEEL
xlsx2pandas-0.1.0.dist-info/top_level.txt
xlsx2pandas-0.1.0.dist-info/RECORD
