Metadata-Version: 2.1
Name: xlsx2pandas
Version: 0.1.0
Summary: Library for obtaining pandas dataframes from xlsx and xlsm files
Author-email: Anton Potapov <fgreyeducation@gmail.com>
License: MIT License
License-File: LICENSE
Requires-Dist: openpyxl
Requires-Dist: pandas
